Metadata-Version: 2.1
Name: FLAVORS
Version: 0.1
Summary: Fast and Lightweight Assessment of Variables for zOptimally-Reduced Subsets towards Feature Learning Automation with Variable-Objective, Resource Scheduling
Home-page: UNKNOWN
Author: Michael Mech
License: UNKNOWN
Platform: UNKNOWN
